samgis_lisa/__init__.py
samgis_lisa/__version__.py
samgis_lisa/io_package/__init__.py
samgis_lisa/io_package/wrappers_helpers.py
samgis_lisa/prediction_api/__init__.py
samgis_lisa/prediction_api/global_models.py
samgis_lisa/prediction_api/lisa.py
samgis_lisa/utilities/__init__.py
samgis_lisa/utilities/constants.py
samgis_lisa/utilities/type_hints.py
samgis_lisa-1.0.10.dist-info/METADATA
samgis_lisa-1.0.10.dist-info/WHEEL
samgis_lisa-1.0.10.dist-info/RECORD
